landmarker-0.3.2.dist-info/METADATA
landmarker-0.3.2.dist-info/WHEEL
landmarker-0.3.2.dist-info/entry_points.txt
landmarker-0.3.2.dist-info/licenses/LICENSE
landmarker/__init__.py
landmarker/data/__init__.py
landmarker/data/landmark_dataset.py
landmarker/datasets/__init__.py
landmarker/datasets/cepha400.py
landmarker/datasets/endovis2015.py
landmarker/datasets/plant_centroids.py
landmarker/heatmap/__init__.py
landmarker/heatmap/decoder.py
landmarker/heatmap/generator.py
landmarker/losses/__init__.py
landmarker/losses/losses.py
landmarker/metrics/__init__.py
landmarker/metrics/metrics.py
landmarker/models/__init__.py
landmarker/models/cholesky_hourglass.py
landmarker/models/coord_conv.py
landmarker/models/hourglass.py
landmarker/models/spatial_configuration_net.py
landmarker/models/utils.py
landmarker/schedulers/__init__.py
landmarker/schedulers/adaloss.py
landmarker/transforms/images.py
landmarker/transforms/landmarks.py
landmarker/uncertainty/__init__.py
landmarker/uncertainty/uncertainty.py
landmarker/utils/__init__.py
landmarker/utils/preprocessing.py
landmarker/utils/utils.py
landmarker/visualize/__init__.py
landmarker/visualize/evaluation.py
landmarker/visualize/utils.py
landmarker-0.3.2.dist-info/RECORD
