Metadata-Version: 2.1
Name: landmarker
Version: 0.3.2
Summary: A PyTorch-based toolkit for (anatomical) landmark detection in images.
Author-Email: Jef Jonkers <jef.jonkers@ugent.be>
License: MIT
Requires-Python: <3.12,>=3.10
Requires-Dist: opencv-python-headless>=4.8.1.78
Requires-Dist: monai>=1.3.0
Requires-Dist: torch>=2.0.0
Requires-Dist: torchvision>=0.15.0
Requires-Dist: tqdm>=4.66.1
Requires-Dist: numpy>=1.24.4
Requires-Dist: pandas>=2.0.3
Requires-Dist: opendatasets>=0.1.22
Requires-Dist: rarfile>=4.1
Requires-Dist: scipy>=1.9.3
Requires-Dist: pydicom>=2.4.3
Requires-Dist: matplotlib>=3.7.4
Requires-Dist: seaborn>=0.13.0
Requires-Dist: scikit-image>=0.21.0
